JOPLEn/__init__.py
JOPLEn/competing.py
JOPLEn/enums.py
JOPLEn/multitask.py
JOPLEn/partitioner.py
JOPLEn/proj_l1_ball.py
JOPLEn/singletask.py
JOPLEn/st_loss.py
JOPLEn/st_penalty.py
joplen-1.0.3.dist-info/LICENSE
joplen-1.0.3.dist-info/METADATA
joplen-1.0.3.dist-info/WHEEL
joplen-1.0.3.dist-info/top_level.txt
joplen-1.0.3.dist-info/RECORD
