Metadata-Version: 2.1
Name: joplen
Version: 1.0.3
Summary: Implementation of Joint Optimization of Piecewise Linear Ensembles (JOPLEn).
Author-email: Matt Raymond <mattrmd@umich.edu>, Angela Violi <avioli@umich.edu>, Clayton Scott <clayscot@umich.edu>
Project-URL: Homepage, https://gitlab.eecs.umich.edu/mattrmd-public/joplen-repositories/joplen
Project-URL: Issue Tracker (Internal), https://gitlab.eecs.umich.edu/mattrmd-public/joplen-repositories/joplen/-/issues
Project-URL: arXiv, https://arxiv.org/abs/2405.00303
Classifier: Programming Language :: Python :: 3
Classifier: License :: OSI Approved :: GNU General Public License v3 (GPLv3)
Classifier: Operating System :: OS Independent
Requires-Python: >=3.10
License-File: LICENSE
Requires-Dist: matplotlib >=3.8.0
Requires-Dist: numpy >=1.24.4
Requires-Dist: scikit-learn >=1.2.0
Requires-Dist: xgboost >=2.0.1
Requires-Dist: linear-tree >=0.3.5
Requires-Dist: catboost >=1.2.5
Requires-Dist: tqdm >=4.66.2
Requires-Dist: setuptools >=64.0.0
Requires-Dist: lightgbm >=4.1.0
